nabla_py/__init__.py
nabla_py/_version.py
nabla_py/basesdk.py
nabla_py/evidence.py
nabla_py/fips.py
nabla_py/firmware.py
nabla_py/httpclient.py
nabla_py/py.typed
nabla_py/sdk.py
nabla_py/sdkconfiguration.py
nabla_py/_hooks/__init__.py
nabla_py/_hooks/registration.py
nabla_py/_hooks/sdkhooks.py
nabla_py/_hooks/types.py
nabla_py/errors/__init__.py
nabla_py/errors/error.py
nabla_py/errors/nabladefaulterror.py
nabla_py/errors/nablaerror.py
nabla_py/errors/no_response_error.py
nabla_py/errors/responsevalidationerror.py
nabla_py/models/__init__.py
nabla_py/models/analyzefirmwarebinary_multipartop.py
nabla_py/models/analyzefirmwarebinaryop.py
nabla_py/models/artifact.py
nabla_py/models/assessazureenvironmentop.py
nabla_py/models/assessmentsummary.py
nabla_py/models/assessterraformstateop.py
nabla_py/models/complianceassessment.py
nabla_py/models/controlassessment.py
nabla_py/models/evidenceresponse.py
nabla_py/models/firmwareresponse.py
nabla_py/models/generatefipsassessmentop.py
nabla_py/models/mappinghit.py
nabla_py/models/security.py
nabla_py/types/__init__.py
nabla_py/types/basemodel.py
nabla_py/utils/__init__.py
nabla_py/utils/annotations.py
nabla_py/utils/datetimes.py
nabla_py/utils/enums.py
nabla_py/utils/eventstreaming.py
nabla_py/utils/forms.py
nabla_py/utils/headers.py
nabla_py/utils/logger.py
nabla_py/utils/metadata.py
nabla_py/utils/queryparams.py
nabla_py/utils/requestbodies.py
nabla_py/utils/retries.py
nabla_py/utils/security.py
nabla_py/utils/serializers.py
nabla_py/utils/unmarshal_json_response.py
nabla_py/utils/url.py
nabla_py/utils/values.py
nabla_py-1.0.0.dist-info/METADATA
nabla_py-1.0.0.dist-info/WHEEL
nabla_py-1.0.0.dist-info/top_level.txt
nabla_py-1.0.0.dist-info/RECORD
