Metadata-Version: 2.4
Name: nabla-py
Version: 1.0.0
Summary: Python Client SDK Generated by Speakeasy.
Author: Speakeasy
Requires-Python: >=3.9.2
Requires-Dist: httpcore>=1.0.9
Requires-Dist: httpx>=0.28.1
Requires-Dist: pydantic>=2.11.2
Requires-Dist: typing_extensions>=4.0.0
